shield/__init__.py
django_shield-0.0.1.dist-info/LICENSE
django_shield-0.0.1.dist-info/METADATA
django_shield-0.0.1.dist-info/WHEEL
django_shield-0.0.1.dist-info/top_level.txt
django_shield-0.0.1.dist-info/RECORD
