Metadata-Version: 2.1
Name: django-shield
Version: 0.0.1
Summary: Per field and per object authorization for Django admin.
Author-email: Jan Bednařík <jan.bednarik@gmail.com>
License: MIT License
Project-URL: Homepage, https://github.com/JanBednarik/django-shield
Project-URL: Bug Tracker, https://github.com/JanBednarik/django-shield/issues
Classifier: Development Status :: 1 - Planning
Classifier: License :: OSI Approved :: MIT License
Classifier: Operating System :: OS Independent
Classifier: Intended Audience :: Developers
Classifier: Programming Language :: Python :: 3
Classifier: Programming Language :: Python :: 3.8
Classifier: Programming Language :: Python :: 3.9
Classifier: Programming Language :: Python :: 3.10
Classifier: Framework :: Django
Classifier: Framework :: Django :: 4.0
Classifier: Topic :: Security
Classifier: Topic :: Software Development :: Libraries :: Python Modules
Requires-Python: >=3.8
License-File: LICENSE
